{"nodes": [{"id": "c_users_manag_downloads_employee_management_system_src_types_hrms_ts", "label": "hrms.ts", "file_type": "code", "source_file": "C:\\Users\\manag\\Downloads\\Employee Management System\\src\\types\\hrms.ts", "source_location": "L1"}, {"id": "types_hrms_employee", "label": "Employee", "file_type": "code", "source_file": "C:\\Users\\manag\\Downloads\\Employee Management System\\src\\types\\hrms.ts", "source_location": "L5"}, {"id": "types_hrms_resignedemployee", "label": "ResignedEmployee", "file_type": "code", "source_file": "C:\\Users\\manag\\Downloads\\Employee Management System\\src\\types\\hrms.ts", "source_location": "L42"}, {"id": "types_hrms_attendancerecord", "label": "AttendanceRecord", "file_type": "code", "source_file": "C:\\Users\\manag\\Downloads\\Employee Management System\\src\\types\\hrms.ts", "source_location": "L58"}, {"id": "types_hrms_leavebalance", "label": "LeaveBalance", "file_type": "code", "source_file": "C:\\Users\\manag\\Downloads\\Employee Management System\\src\\types\\hrms.ts", "source_location": "L70"}, {"id": "types_hrms_leavehistoryrecord", "label": "LeaveHistoryRecord", "file_type": "code", "source_file": "C:\\Users\\manag\\Downloads\\Employee Management System\\src\\types\\hrms.ts", "source_location": "L84"}, {"id": "types_hrms_payrollsummary", "label": "PayrollSummary", "file_type": "code", "source_file": "C:\\Users\\manag\\Downloads\\Employee Management System\\src\\types\\hrms.ts", "source_location": "L94"}, {"id": "types_hrms_plrecord", "label": "PLRecord", "file_type": "code", "source_file": "C:\\Users\\manag\\Downloads\\Employee Management System\\src\\types\\hrms.ts", "source_location": "L114"}, {"id": "types_hrms_historyrecord", "label": "HistoryRecord", "file_type": "code", "source_file": "C:\\Users\\manag\\Downloads\\Employee Management System\\src\\types\\hrms.ts", "source_location": "L128"}, {"id": "types_hrms_dashboardstats", "label": "DashboardStats", "file_type": "code", "source_file": "C:\\Users\\manag\\Downloads\\Employee Management System\\src\\types\\hrms.ts", "source_location": "L142"}, {"id": "types_hrms_letter", "label": "Letter", "file_type": "code", "source_file": "C:\\Users\\manag\\Downloads\\Employee Management System\\src\\types\\hrms.ts", "source_location": "L186"}, {"id": "types_hrms_toastmessage", "label": "ToastMessage", "file_type": "code", "source_file": "C:\\Users\\manag\\Downloads\\Employee Management System\\src\\types\\hrms.ts", "source_location": "L219"}], "edges": [{"source": "c_users_manag_downloads_employee_management_system_src_types_hrms_ts", "target": "types_hrms_employee", "relation": "contains", "confidence": "EXTRACTED", "source_file": "C:\\Users\\manag\\Downloads\\Employee Management System\\src\\types\\hrms.ts", "source_location": "L5", "weight": 1.0}, {"source": "c_users_manag_downloads_employee_management_system_src_types_hrms_ts", "target": "types_hrms_resignedemployee", "relation": "contains", "confidence": "EXTRACTED", "source_file": "C:\\Users\\manag\\Downloads\\Employee Management System\\src\\types\\hrms.ts", "source_location": "L42", "weight": 1.0}, {"source": "c_users_manag_downloads_employee_management_system_src_types_hrms_ts", "target": "types_hrms_attendancerecord", "relation": "contains", "confidence": "EXTRACTED", "source_file": "C:\\Users\\manag\\Downloads\\Employee Management System\\src\\types\\hrms.ts", "source_location": "L58", "weight": 1.0}, {"source": "c_users_manag_downloads_employee_management_system_src_types_hrms_ts", "target": "types_hrms_leavebalance", "relation": "contains", "confidence": "EXTRACTED", "source_file": "C:\\Users\\manag\\Downloads\\Employee Management System\\src\\types\\hrms.ts", "source_location": "L70", "weight": 1.0}, {"source": "c_users_manag_downloads_employee_management_system_src_types_hrms_ts", "target": "types_hrms_leavehistoryrecord", "relation": "contains", "confidence": "EXTRACTED", "source_file": "C:\\Users\\manag\\Downloads\\Employee Management System\\src\\types\\hrms.ts", "source_location": "L84", "weight": 1.0}, {"source": "c_users_manag_downloads_employee_management_system_src_types_hrms_ts", "target": "types_hrms_payrollsummary", "relation": "contains", "confidence": "EXTRACTED", "source_file": "C:\\Users\\manag\\Downloads\\Employee Management System\\src\\types\\hrms.ts", "source_location": "L94", "weight": 1.0}, {"source": "c_users_manag_downloads_employee_management_system_src_types_hrms_ts", "target": "types_hrms_plrecord", "relation": "contains", "confidence": "EXTRACTED", "source_file": "C:\\Users\\manag\\Downloads\\Employee Management System\\src\\types\\hrms.ts", "source_location": "L114", "weight": 1.0}, {"source": "c_users_manag_downloads_employee_management_system_src_types_hrms_ts", "target": "types_hrms_historyrecord", "relation": "contains", "confidence": "EXTRACTED", "source_file": "C:\\Users\\manag\\Downloads\\Employee Management System\\src\\types\\hrms.ts", "source_location": "L128", "weight": 1.0}, {"source": "c_users_manag_downloads_employee_management_system_src_types_hrms_ts", "target": "types_hrms_dashboardstats", "relation": "contains", "confidence": "EXTRACTED", "source_file": "C:\\Users\\manag\\Downloads\\Employee Management System\\src\\types\\hrms.ts", "source_location": "L142", "weight": 1.0}, {"source": "c_users_manag_downloads_employee_management_system_src_types_hrms_ts", "target": "types_hrms_letter", "relation": "contains", "confidence": "EXTRACTED", "source_file": "C:\\Users\\manag\\Downloads\\Employee Management System\\src\\types\\hrms.ts", "source_location": "L186", "weight": 1.0}, {"source": "c_users_manag_downloads_employee_management_system_src_types_hrms_ts", "target": "types_hrms_toastmessage", "relation": "contains", "confidence": "EXTRACTED", "source_file": "C:\\Users\\manag\\Downloads\\Employee Management System\\src\\types\\hrms.ts", "source_location": "L219", "weight": 1.0}], "raw_calls": []}